{
  "title": "topbeat-cpu-user-per-host",
  "visState": "{\"title\":\"topbeat-cpu-user-per-host\",\"type\":\"line\",\"params\":{\"shareYAxis\":true,\"addTooltip\":true,\"addLegend\":true,\"showCircles\":true,\"smoothLines\":false,\"interpolate\":\"linear\",\"scale\":\"linear\",\"drawLinesBetweenPoints\":true,\"radiusRatio\":9,\"times\":[],\"addTimeMarker\":false,\"defaultYExtents\":false,\"setYExtents\":true,\"yAxis\":{\"max\":1,\"min\":0}},\"aggs\":[{\"id\":\"1\",\"type\":\"max\",\"schema\":\"metric\",\"params\":{\"field\":\"cpu.user_p\",\"customLabel\":\"CPU usage\"}},{\"id\":\"2\",\"type\":\"date_histogram\",\"schema\":\"segment\",\"params\":{\"field\":\"@timestamp\",\"interval\":\"auto\",\"customInterval\":\"2h\",\"min_doc_count\":1,\"extended_bounds\":{}}},{\"id\":\"3\",\"type\":\"terms\",\"schema\":\"group\",\"params\":{\"field\":\"beat.hostname\",\"size\":100,\"order\":\"desc\",\"orderBy\":\"_term\"}}],\"listeners\":{}}",
  "uiStateJSON": "{}",
  "description": "",
  "savedSearchId": "topbeat-system",
  "version": 1,
  "kibanaSavedObjectMeta": {
    "searchSourceJSON": "{\"filter\":[]}"
  }
}
